file_replicator/__init__.py
file_replicator/cli.py
file_replicator/lib.py
file_replicator-0.1.11.dist-info/entry_points.txt
file_replicator-0.1.11.dist-info/LICENSE
file_replicator-0.1.11.dist-info/WHEEL
file_replicator-0.1.11.dist-info/METADATA
file_replicator-0.1.11.dist-info/RECORD
